tfwrapper/__init__.py
tfwrapper/exceptions.py
tfwrapper/lock.py
tfwrapper/run.py
tfwrapper-0.0.1a15.data/scripts/tfwrapper
tfwrapper-0.0.1a15.dist-info/DESCRIPTION.rst
tfwrapper-0.0.1a15.dist-info/METADATA
tfwrapper-0.0.1a15.dist-info/RECORD
tfwrapper-0.0.1a15.dist-info/WHEEL
tfwrapper-0.0.1a15.dist-info/metadata.json
tfwrapper-0.0.1a15.dist-info/top_level.txt
